alibabacloud_acc20240402/__init__.py
alibabacloud_acc20240402/client.py
alibabacloud_acc20240402/models/__init__.py
alibabacloud_acc20240402/models/_capacity_resource.py
alibabacloud_acc20240402/models/_create_image_cache_request.py
alibabacloud_acc20240402/models/_create_image_cache_response.py
alibabacloud_acc20240402/models/_create_image_cache_response_body.py
alibabacloud_acc20240402/models/_create_image_cache_shrink_request.py
alibabacloud_acc20240402/models/_delete_image_cache_request.py
alibabacloud_acc20240402/models/_delete_image_cache_response.py
alibabacloud_acc20240402/models/_delete_image_cache_response_body.py
alibabacloud_acc20240402/models/_get_image_cache_request.py
alibabacloud_acc20240402/models/_get_image_cache_response.py
alibabacloud_acc20240402/models/_get_image_cache_response_body.py
alibabacloud_acc20240402/models/_list_image_caches_request.py
alibabacloud_acc20240402/models/_list_image_caches_response.py
alibabacloud_acc20240402/models/_list_image_caches_response_body.py
alibabacloud_acc20240402-2.0.1.dist-info/LICENSE
alibabacloud_acc20240402-2.0.1.dist-info/METADATA
alibabacloud_acc20240402-2.0.1.dist-info/WHEEL
alibabacloud_acc20240402-2.0.1.dist-info/top_level.txt
alibabacloud_acc20240402-2.0.1.dist-info/RECORD
